grand_challenge_forge/__init__.py
grand_challenge_forge/cli.py
grand_challenge_forge/exceptions.py
grand_challenge_forge/forge.py
grand_challenge_forge/generation_utils.py
grand_challenge_forge/partials/algorithm-template-readme/README.md.j2
grand_challenge_forge/partials/example-algorithm/.gitattributes.j2
grand_challenge_forge/partials/example-algorithm/Dockerfile
grand_challenge_forge/partials/example-algorithm/do_build.sh.j2
grand_challenge_forge/partials/example-algorithm/do_save.sh.j2
grand_challenge_forge/partials/example-algorithm/do_test_run.sh.j2
grand_challenge_forge/partials/example-algorithm/inference.py.j2
grand_challenge_forge/partials/example-algorithm/model/README.md
grand_challenge_forge/partials/example-algorithm/model/a_tarball_subdirectory/some_tarball_resource.txt
grand_challenge_forge/partials/example-algorithm/requirements.txt.j2
grand_challenge_forge/partials/example-algorithm/resources/README.md
grand_challenge_forge/partials/example-algorithm/resources/some_resource.txt
grand_challenge_forge/partials/example-algorithm/test/.gitignore
grand_challenge_forge/partials/example-evaluation-method/Dockerfile
grand_challenge_forge/partials/example-evaluation-method/do_build.sh.j2
grand_challenge_forge/partials/example-evaluation-method/do_save.sh.j2
grand_challenge_forge/partials/example-evaluation-method/do_test_run.sh.j2
grand_challenge_forge/partials/example-evaluation-method/evaluate.py.j2
grand_challenge_forge/partials/example-evaluation-method/ground_truth/README.md
grand_challenge_forge/partials/example-evaluation-method/ground_truth/a_tarball_subdirectory/some_tarball_resource.txt
grand_challenge_forge/partials/example-evaluation-method/helpers.py
grand_challenge_forge/partials/example-evaluation-method/requirements.txt.j2
grand_challenge_forge/partials/example-evaluation-method/resources/README.md
grand_challenge_forge/partials/example-evaluation-method/resources/some_resource.txt
grand_challenge_forge/partials/filters.py
grand_challenge_forge-0.7.5.dist-info/LICENSE
grand_challenge_forge-0.7.5.dist-info/METADATA
grand_challenge_forge-0.7.5.dist-info/WHEEL
grand_challenge_forge-0.7.5.dist-info/entry_points.txt
grand_challenge_forge-0.7.5.dist-info/RECORD
