Metadata-Version: 2.3
Name: grand-challenge-forge
Version: 0.7.5
Summary: Generation of challenge packs
License: Apache-2.0
Author: Chris van Run
Requires-Python: >3.10
Classifier: Development Status :: 3 - Alpha
Classifier: Intended Audience :: Developers
Classifier: Intended Audience :: Healthcare Industry
Classifier: License :: OSI Approved :: Apache Software License
Classifier: Operating System :: POSIX
Classifier: Programming Language :: Python :: 3
Classifier: Programming Language :: Python :: 3.11
Classifier: Programming Language :: Python :: 3.12
Classifier: Programming Language :: Python :: 3.13
Requires-Dist: black
Requires-Dist: click
Requires-Dist: jinja2
Requires-Dist: jsonschema
Project-URL: Repository, https://github.com/DIAGNijmegen/rse-grand-challenge-forge
